microsignal/__init__.py
microsignal/microsignal.py
microsignal-0.1.1.dist-info/LICENSE
microsignal-0.1.1.dist-info/METADATA
microsignal-0.1.1.dist-info/WHEEL
microsignal-0.1.1.dist-info/top_level.txt
microsignal-0.1.1.dist-info/RECORD
