Metadata-Version: 2.1
Name: microsignal
Version: 0.1.1
Summary: A lightweight library for handling custom signals with synchronous and asynchronous callbacks in Python.
Home-page: https://github.com/taraant/microsignal
Author: Tarasov Anton (taraant)
Author-email: ant0@mail.ru
Classifier: Programming Language :: Python :: 3
Classifier: License :: OSI Approved :: GNU General Public License v3 (GPLv3)
Classifier: Operating System :: OS Independent
Requires-Python: >=3.6
License-File: LICENSE
